{
  "timestamp": "2026-03-30 12:34:14",
  "script": "scripts/benchmarking/paper_keep_ratio_repeat.py",
  "output_schema_version": "1.0",
  "experiment": "E1_keep_ratio_repeat",
  "config": {
    "model_path": "/Users/delete/Desktop/rag_system_副本/models/Llama-3-8B-Instruct.Q4_K_M.gguf",
    "index_path": "/Users/delete/Desktop/rag_system_副本/models/vector_indices/turbo_index.json",
    "ratios": [
      1.0,
      0.9,
      0.8,
      0.7,
      0.6,
      0.5,
      0.4,
      0.3,
      0.2
    ],
    "rounds": 5,
    "n_ctx": 4096,
    "top_k": 15,
    "num_docs": 25,
    "doc_repeat": 2,
    "query": "What execution bottlenecks dominate local RAG on constrained unified-memory hardware?"
  },
  "rows": [
    {
      "keep_ratio": 1.0,
      "runs": [
        {
          "keep_ratio": 1.0,
          "retrieval_ms": 0.005333,
          "scoring_ms": 518.623834,
          "pruning_ms": 0.07558300000005147,
          "ttft_ms": 3626.097084,
          "decode_tps": 17.87402263394301,
          "total_e2e_ms": 9515.724875,
          "generated_tokens": 96,
          "original_len": 12678,
          "compressed_len": 3516,
          "strategy": "static_ratio_100.0% (capped_at_10)"
        },
        {
          "keep_ratio": 1.0,
          "retrieval_ms": 0.001208,
          "scoring_ms": 157.5935,
          "pruning_ms": 0.07004200000000083,
          "ttft_ms": 142.508417,
          "decode_tps": 16.196974748257297,
          "total_e2e_ms": 7091.564875,
          "generated_tokens": 110,
          "original_len": 12678,
          "compressed_len": 3516,
          "strategy": "static_ratio_100.0% (capped_at_10)"
        },
        {
          "keep_ratio": 1.0,
          "retrieval_ms": 0.00125,
          "scoring_ms": 110.844375,
          "pruning_ms": 0.04075000000000273,
          "ttft_ms": 117.486334,
          "decode_tps": 16.998101614152322,
          "total_e2e_ms": 5405.4214170000005,
          "generated_tokens": 88,
          "original_len": 12678,
          "compressed_len": 3516,
          "strategy": "static_ratio_100.0% (capped_at_10)"
        },
        {
          "keep_ratio": 1.0,
          "retrieval_ms": 0.001375,
          "scoring_ms": 103.841333,
          "pruning_ms": 0.0815419999999989,
          "ttft_ms": 121.935958,
          "decode_tps": 17.094371220345323,
          "total_e2e_ms": 7772.203875,
          "generated_tokens": 129,
          "original_len": 12678,
          "compressed_len": 3516,
          "strategy": "static_ratio_100.0% (capped_at_10)"
        },
        {
          "keep_ratio": 1.0,
          "retrieval_ms": 0.001292,
          "scoring_ms": 141.26275,
          "pruning_ms": 0.06116699999998332,
          "ttft_ms": 117.997667,
          "decode_tps": 16.908083380995812,
          "total_e2e_ms": 7652.236501,
          "generated_tokens": 125,
          "original_len": 12678,
          "compressed_len": 3516,
          "strategy": "static_ratio_100.0% (capped_at_10)"
        }
      ],
      "selected_candidate": false,
      "strategies_used": [
        "static_ratio_100.0% (capped_at_10)"
      ],
      "retrieval_ms_mean": 0.002,
      "retrieval_ms_std": 0.002,
      "scoring_ms_mean": 206.433,
      "scoring_ms_std": 157.326,
      "pruning_ms_mean": 0.066,
      "pruning_ms_std": 0.014,
      "ttft_ms_mean": 825.205,
      "ttft_ms_std": 1400.476,
      "ttft_ms_p95": 2929.379,
      "decode_tps_mean": 17.014,
      "decode_tps_std": 0.534,
      "total_e2e_ms_mean": 7487.43,
      "total_e2e_ms_std": 1320.129,
      "total_e2e_ms_p95": 9167.021,
      "generated_tokens_mean": 109.6,
      "generated_tokens_std": 15.907,
      "original_len_mean": 12678.0,
      "original_len_std": 0.0,
      "compressed_len_mean": 3516.0,
      "compressed_len_std": 0.0
    },
    {
      "keep_ratio": 0.9,
      "runs": [
        {
          "keep_ratio": 0.9,
          "retrieval_ms": 0.001833,
          "scoring_ms": 129.711667,
          "pruning_ms": 0.04245799999998212,
          "ttft_ms": 3213.251875,
          "decode_tps": 16.190456743692884,
          "total_e2e_ms": 10445.957541,
          "generated_tokens": 115,
          "original_len": 12678,
          "compressed_len": 3515,
          "strategy": "static_ratio_90.0% (capped_at_10)"
        },
        {
          "keep_ratio": 0.9,
          "retrieval_ms": 0.001209,
          "scoring_ms": 150.413,
          "pruning_ms": 0.055542000000002645,
          "ttft_ms": 126.456917,
          "decode_tps": 16.941408599126834,
          "total_e2e_ms": 5353.2460009999995,
          "generated_tokens": 86,
          "original_len": 12678,
          "compressed_len": 3515,
          "strategy": "static_ratio_90.0% (capped_at_10)"
        },
        {
          "keep_ratio": 0.9,
          "retrieval_ms": 0.001417,
          "scoring_ms": 99.223,
          "pruning_ms": 0.036874999999994884,
          "ttft_ms": 119.590875,
          "decode_tps": 17.175285571709665,
          "total_e2e_ms": 5109.600542,
          "generated_tokens": 84,
          "original_len": 12678,
          "compressed_len": 3515,
          "strategy": "static_ratio_90.0% (capped_at_10)"
        },
        {
          "keep_ratio": 0.9,
          "retrieval_ms": 0.00225,
          "scoring_ms": 119.29675,
          "pruning_ms": 0.05124999999999602,
          "ttft_ms": 120.546416,
          "decode_tps": 17.235123185147465,
          "total_e2e_ms": 5461.791458,
          "generated_tokens": 90,
          "original_len": 12678,
          "compressed_len": 3515,
          "strategy": "static_ratio_90.0% (capped_at_10)"
        },
        {
          "keep_ratio": 0.9,
          "retrieval_ms": 0.001125,
          "scoring_ms": 89.192041,
          "pruning_ms": 0.03666699999999423,
          "ttft_ms": 116.927542,
          "decode_tps": 15.57726340791713,
          "total_e2e_ms": 5919.612791999999,
          "generated_tokens": 89,
          "original_len": 12678,
          "compressed_len": 3515,
          "strategy": "static_ratio_90.0% (capped_at_10)"
        }
      ],
      "selected_candidate": false,
      "strategies_used": [
        "static_ratio_90.0% (capped_at_10)"
      ],
      "retrieval_ms_mean": 0.002,
      "retrieval_ms_std": 0.0,
      "scoring_ms_mean": 117.567,
      "scoring_ms_std": 21.776,
      "pruning_ms_mean": 0.045,
      "pruning_ms_std": 0.008,
      "ttft_ms_mean": 739.355,
      "ttft_ms_std": 1236.952,
      "ttft_ms_p95": 2595.893,
      "decode_tps_mean": 16.624,
      "decode_tps_std": 0.642,
      "total_e2e_ms_mean": 6458.042,
      "total_e2e_ms_std": 2011.207,
      "total_e2e_ms_p95": 9540.689,
      "generated_tokens_mean": 92.8,
      "generated_tokens_std": 11.303,
      "original_len_mean": 12678.0,
      "original_len_std": 0.0,
      "compressed_len_mean": 3515.0,
      "compressed_len_std": 0.0
    },
    {
      "keep_ratio": 0.8,
      "runs": [
        {
          "keep_ratio": 0.8,
          "retrieval_ms": 0.001292,
          "scoring_ms": 141.408541,
          "pruning_ms": 0.057167999999990116,
          "ttft_ms": 3194.612584,
          "decode_tps": 13.180442267171285,
          "total_e2e_ms": 11681.778293,
          "generated_tokens": 110,
          "original_len": 12678,
          "compressed_len": 3515,
          "strategy": "static_ratio_80.0% (capped_at_10)"
        },
        {
          "keep_ratio": 0.8,
          "retrieval_ms": 0.001458,
          "scoring_ms": 162.292375,
          "pruning_ms": 0.09104200000001583,
          "ttft_ms": 137.228,
          "decode_tps": 17.671960332065723,
          "total_e2e_ms": 7599.3123749999995,
          "generated_tokens": 129,
          "original_len": 12678,
          "compressed_len": 3515,
          "strategy": "static_ratio_80.0% (capped_at_10)"
        },
        {
          "keep_ratio": 0.8,
          "retrieval_ms": 0.002583,
          "scoring_ms": 115.4735,
          "pruning_ms": 0.05620799999999804,
          "ttft_ms": 115.585583,
          "decode_tps": 18.222516846637014,
          "total_e2e_ms": 7310.271707999999,
          "generated_tokens": 129,
          "original_len": 12678,
          "compressed_len": 3515,
          "strategy": "static_ratio_80.0% (capped_at_10)"
        },
        {
          "keep_ratio": 0.8,
          "retrieval_ms": 0.001166,
          "scoring_ms": 77.693958,
          "pruning_ms": 0.03679200000000549,
          "ttft_ms": 112.764375,
          "decode_tps": 18.434631064691537,
          "total_e2e_ms": 5452.331999000001,
          "generated_tokens": 97,
          "original_len": 12678,
          "compressed_len": 3515,
          "strategy": "static_ratio_80.0% (capped_at_10)"
        },
        {
          "keep_ratio": 0.8,
          "retrieval_ms": 0.003375,
          "scoring_ms": 85.754,
          "pruning_ms": 0.05187499999999545,
          "ttft_ms": 110.721667,
          "decode_tps": 18.028070985698314,
          "total_e2e_ms": 5077.807459000001,
          "generated_tokens": 88,
          "original_len": 12678,
          "compressed_len": 3515,
          "strategy": "static_ratio_80.0% (capped_at_10)"
        }
      ],
      "selected_candidate": false,
      "strategies_used": [
        "static_ratio_80.0% (capped_at_10)"
      ],
      "retrieval_ms_mean": 0.002,
      "retrieval_ms_std": 0.001,
      "scoring_ms_mean": 116.524,
      "scoring_ms_std": 32.155,
      "pruning_ms_mean": 0.059,
      "pruning_ms_std": 0.018,
      "ttft_ms_mean": 734.182,
      "ttft_ms_std": 1230.252,
      "ttft_ms_p95": 2583.136,
      "decode_tps_mean": 17.108,
      "decode_tps_std": 1.98,
      "total_e2e_ms_mean": 7424.3,
      "total_e2e_ms_std": 2347.954,
      "total_e2e_ms_p95": 10865.285,
      "generated_tokens_mean": 110.6,
      "generated_tokens_std": 16.572,
      "original_len_mean": 12678.0,
      "original_len_std": 0.0,
      "compressed_len_mean": 3515.0,
      "compressed_len_std": 0.0
    },
    {
      "keep_ratio": 0.7,
      "runs": [
        {
          "keep_ratio": 0.7,
          "retrieval_ms": 0.00325,
          "scoring_ms": 98.22875,
          "pruning_ms": 0.05104199999999537,
          "ttft_ms": 2899.605,
          "decode_tps": 17.940531947251234,
          "total_e2e_ms": 7624.28375,
          "generated_tokens": 83,
          "original_len": 12678,
          "compressed_len": 3515,
          "strategy": "static_ratio_70.0% (capped_at_10)"
        },
        {
          "keep_ratio": 0.7,
          "retrieval_ms": 0.002,
          "scoring_ms": 86.527792,
          "pruning_ms": 0.04391599999999585,
          "ttft_ms": 120.604708,
          "decode_tps": 18.08774295500242,
          "total_e2e_ms": 4961.779375,
          "generated_tokens": 86,
          "original_len": 12678,
          "compressed_len": 3515,
          "strategy": "static_ratio_70.0% (capped_at_10)"
        },
        {
          "keep_ratio": 0.7,
          "retrieval_ms": 0.004209,
          "scoring_ms": 96.969166,
          "pruning_ms": 0.0631259999999969,
          "ttft_ms": 117.789084,
          "decode_tps": 18.52682721857695,
          "total_e2e_ms": 4478.912418,
          "generated_tokens": 79,
          "original_len": 12678,
          "compressed_len": 3515,
          "strategy": "static_ratio_70.0% (capped_at_10)"
        },
        {
          "keep_ratio": 0.7,
          "retrieval_ms": 0.005958,
          "scoring_ms": 90.92475,
          "pruning_ms": 0.07183399999999551,
          "ttft_ms": 109.01325,
          "decode_tps": 18.250916820340542,
          "total_e2e_ms": 5021.691375,
          "generated_tokens": 88,
          "original_len": 12678,
          "compressed_len": 3515,
          "strategy": "static_ratio_70.0% (capped_at_10)"
        },
        {
          "keep_ratio": 0.7,
          "retrieval_ms": 0.001209,
          "scoring_ms": 77.674166,
          "pruning_ms": 0.04370900000000688,
          "ttft_ms": 119.532125,
          "decode_tps": 17.91133041597004,
          "total_e2e_ms": 6785.259875000001,
          "generated_tokens": 118,
          "original_len": 12678,
          "compressed_len": 3515,
          "strategy": "static_ratio_70.0% (capped_at_10)"
        }
      ],
      "selected_candidate": false,
      "strategies_used": [
        "static_ratio_70.0% (capped_at_10)"
      ],
      "retrieval_ms_mean": 0.003,
      "retrieval_ms_std": 0.002,
      "scoring_ms_mean": 90.065,
      "scoring_ms_std": 7.498,
      "pruning_ms_mean": 0.055,
      "pruning_ms_std": 0.011,
      "ttft_ms_mean": 673.309,
      "ttft_ms_std": 1113.156,
      "ttft_ms_p95": 2343.805,
      "decode_tps_mean": 18.143,
      "decode_tps_std": 0.227,
      "total_e2e_ms_mean": 5774.385,
      "total_e2e_ms_std": 1212.363,
      "total_e2e_ms_p95": 7456.479,
      "generated_tokens_mean": 90.8,
      "generated_tokens_std": 13.934,
      "original_len_mean": 12678.0,
      "original_len_std": 0.0,
      "compressed_len_mean": 3515.0,
      "compressed_len_std": 0.0
    },
    {
      "keep_ratio": 0.6,
      "runs": [
        {
          "keep_ratio": 0.6,
          "retrieval_ms": 0.003125,
          "scoring_ms": 90.184209,
          "pruning_ms": 0.04620800000000713,
          "ttft_ms": 2768.692583,
          "decode_tps": 17.588362375184794,
          "total_e2e_ms": 10193.321292,
          "generated_tokens": 129,
          "original_len": 12678,
          "compressed_len": 3515,
          "strategy": "static_ratio_60.0% (capped_at_10)"
        },
        {
          "keep_ratio": 0.6,
          "retrieval_ms": 0.003292,
          "scoring_ms": 92.8665,
          "pruning_ms": 0.0504579999999919,
          "ttft_ms": 120.294833,
          "decode_tps": 15.017534499474962,
          "total_e2e_ms": 8803.173707999998,
          "generated_tokens": 129,
          "original_len": 12678,
          "compressed_len": 3515,
          "strategy": "static_ratio_60.0% (capped_at_10)"
        },
        {
          "keep_ratio": 0.6,
          "retrieval_ms": 0.00225,
          "scoring_ms": 133.866708,
          "pruning_ms": 0.07875000000001364,
          "ttft_ms": 138.545292,
          "decode_tps": 15.208541824462658,
          "total_e2e_ms": 8754.5685,
          "generated_tokens": 129,
          "original_len": 12678,
          "compressed_len": 3515,
          "strategy": "static_ratio_60.0% (capped_at_10)"
        },
        {
          "keep_ratio": 0.6,
          "retrieval_ms": 0.001417,
          "scoring_ms": 144.48,
          "pruning_ms": 0.038000000000010914,
          "ttft_ms": 133.863667,
          "decode_tps": 15.222201468914458,
          "total_e2e_ms": 4745.542459,
          "generated_tokens": 68,
          "original_len": 12678,
          "compressed_len": 3515,
          "strategy": "static_ratio_60.0% (capped_at_10)"
        },
        {
          "keep_ratio": 0.6,
          "retrieval_ms": 0.001291,
          "scoring_ms": 115.154708,
          "pruning_ms": 0.07145900000000438,
          "ttft_ms": 135.2125,
          "decode_tps": 14.961455164730644,
          "total_e2e_ms": 8337.888583000002,
          "generated_tokens": 121,
          "original_len": 12678,
          "compressed_len": 3515,
          "strategy": "static_ratio_60.0% (capped_at_10)"
        }
      ],
      "selected_candidate": true,
      "strategies_used": [
        "static_ratio_60.0% (capped_at_10)"
      ],
      "retrieval_ms_mean": 0.002,
      "retrieval_ms_std": 0.001,
      "scoring_ms_mean": 115.31,
      "scoring_ms_std": 21.588,
      "pruning_ms_mean": 0.057,
      "pruning_ms_std": 0.016,
      "ttft_ms_mean": 659.322,
      "ttft_ms_std": 1054.704,
      "ttft_ms_p95": 2242.663,
      "decode_tps_mean": 15.6,
      "decode_tps_std": 1.0,
      "total_e2e_ms_mean": 8166.899,
      "total_e2e_ms_std": 1821.621,
      "total_e2e_ms_p95": 9915.292,
      "generated_tokens_mean": 115.2,
      "generated_tokens_std": 23.803,
      "original_len_mean": 12678.0,
      "original_len_std": 0.0,
      "compressed_len_mean": 3515.0,
      "compressed_len_std": 0.0
    },
    {
      "keep_ratio": 0.5,
      "runs": [
        {
          "keep_ratio": 0.5,
          "retrieval_ms": 0.001875,
          "scoring_ms": 105.885792,
          "pruning_ms": 0.05162400000000389,
          "ttft_ms": 3283.331666,
          "decode_tps": 15.489478396282282,
          "total_e2e_ms": 10684.545666,
          "generated_tokens": 113,
          "original_len": 12678,
          "compressed_len": 3515,
          "strategy": "static_ratio_50.0% (capped_at_10)"
        },
        {
          "keep_ratio": 0.5,
          "retrieval_ms": 0.001292,
          "scoring_ms": 132.678042,
          "pruning_ms": 0.04741599999999835,
          "ttft_ms": 145.679125,
          "decode_tps": 16.77960692092462,
          "total_e2e_ms": 5761.251834000001,
          "generated_tokens": 92,
          "original_len": 12678,
          "compressed_len": 3515,
          "strategy": "static_ratio_50.0% (capped_at_10)"
        },
        {
          "keep_ratio": 0.5,
          "retrieval_ms": 0.002209,
          "scoring_ms": 108.213084,
          "pruning_ms": 0.05487399999999809,
          "ttft_ms": 111.969709,
          "decode_tps": 18.18918161847093,
          "total_e2e_ms": 5882.946542,
          "generated_tokens": 103,
          "original_len": 12678,
          "compressed_len": 3515,
          "strategy": "static_ratio_50.0% (capped_at_10)"
        },
        {
          "keep_ratio": 0.5,
          "retrieval_ms": 0.0015,
          "scoring_ms": 88.600875,
          "pruning_ms": 0.03829199999999844,
          "ttft_ms": 130.623958,
          "decode_tps": 13.104776936232268,
          "total_e2e_ms": 10063.003333999999,
          "generated_tokens": 129,
          "original_len": 12678,
          "compressed_len": 3515,
          "strategy": "static_ratio_50.0% (capped_at_10)"
        },
        {
          "keep_ratio": 0.5,
          "retrieval_ms": 0.001625,
          "scoring_ms": 301.268709,
          "pruning_ms": 0.07466599999997925,
          "ttft_ms": 172.271,
          "decode_tps": 15.122130206520648,
          "total_e2e_ms": 6623.543208,
          "generated_tokens": 93,
          "original_len": 12678,
          "compressed_len": 3515,
          "strategy": "static_ratio_50.0% (capped_at_10)"
        }
      ],
      "selected_candidate": false,
      "strategies_used": [
        "static_ratio_50.0% (capped_at_10)"
      ],
      "retrieval_ms_mean": 0.002,
      "retrieval_ms_std": 0.0,
      "scoring_ms_mean": 147.329,
      "scoring_ms_std": 78.242,
      "pruning_ms_mean": 0.053,
      "pruning_ms_std": 0.012,
      "ttft_ms_mean": 768.775,
      "ttft_ms_std": 1257.433,
      "ttft_ms_p95": 2661.12,
      "decode_tps_mean": 15.737,
      "decode_tps_std": 1.701,
      "total_e2e_ms_mean": 7803.058,
      "total_e2e_ms_std": 2128.726,
      "total_e2e_ms_p95": 10560.237,
      "generated_tokens_mean": 106.0,
      "generated_tokens_std": 13.799,
      "original_len_mean": 12678.0,
      "original_len_std": 0.0,
      "compressed_len_mean": 3515.0,
      "compressed_len_std": 0.0
    },
    {
      "keep_ratio": 0.4,
      "runs": [
        {
          "keep_ratio": 0.4,
          "retrieval_ms": 0.002708,
          "scoring_ms": 122.597541,
          "pruning_ms": 0.04479199999998684,
          "ttft_ms": 3203.919458,
          "decode_tps": 15.894363127368786,
          "total_e2e_ms": 8548.541582,
          "generated_tokens": 83,
          "original_len": 12678,
          "compressed_len": 3515,
          "strategy": "static_ratio_40.0% (capped_at_10)"
        },
        {
          "keep_ratio": 0.4,
          "retrieval_ms": 0.002416,
          "scoring_ms": 108.959334,
          "pruning_ms": 0.04808300000000543,
          "ttft_ms": 128.65,
          "decode_tps": 15.755127670910383,
          "total_e2e_ms": 6648.271166,
          "generated_tokens": 101,
          "original_len": 12678,
          "compressed_len": 3515,
          "strategy": "static_ratio_40.0% (capped_at_10)"
        },
        {
          "keep_ratio": 0.4,
          "retrieval_ms": 0.001291,
          "scoring_ms": 118.142083,
          "pruning_ms": 0.040374999999997385,
          "ttft_ms": 130.524083,
          "decode_tps": 15.833937531044766,
          "total_e2e_ms": 6627.41179,
          "generated_tokens": 101,
          "original_len": 12678,
          "compressed_len": 3515,
          "strategy": "static_ratio_40.0% (capped_at_10)"
        },
        {
          "keep_ratio": 0.4,
          "retrieval_ms": 0.001375,
          "scoring_ms": 156.022833,
          "pruning_ms": 0.05354200000002152,
          "ttft_ms": 131.597667,
          "decode_tps": 15.846783551710086,
          "total_e2e_ms": 8428.128625000001,
          "generated_tokens": 129,
          "original_len": 12678,
          "compressed_len": 3515,
          "strategy": "static_ratio_40.0% (capped_at_10)"
        },
        {
          "keep_ratio": 0.4,
          "retrieval_ms": 0.001375,
          "scoring_ms": 131.841708,
          "pruning_ms": 0.03687499999998067,
          "ttft_ms": 129.594167,
          "decode_tps": 16.023674023279295,
          "total_e2e_ms": 5316.494583,
          "generated_tokens": 81,
          "original_len": 12678,
          "compressed_len": 3515,
          "strategy": "static_ratio_40.0% (capped_at_10)"
        }
      ],
      "selected_candidate": false,
      "strategies_used": [
        "static_ratio_40.0% (capped_at_10)"
      ],
      "retrieval_ms_mean": 0.002,
      "retrieval_ms_std": 0.001,
      "scoring_ms_mean": 127.513,
      "scoring_ms_std": 16.048,
      "pruning_ms_mean": 0.045,
      "pruning_ms_std": 0.006,
      "ttft_ms_mean": 744.857,
      "ttft_ms_std": 1229.532,
      "ttft_ms_p95": 2589.455,
      "decode_tps_mean": 15.871,
      "decode_tps_std": 0.089,
      "total_e2e_ms_mean": 7113.77,
      "total_e2e_ms_std": 1222.255,
      "total_e2e_ms_p95": 8524.459,
      "generated_tokens_mean": 99.0,
      "generated_tokens_std": 17.251,
      "original_len_mean": 12678.0,
      "original_len_std": 0.0,
      "compressed_len_mean": 3515.0,
      "compressed_len_std": 0.0
    },
    {
      "keep_ratio": 0.3,
      "runs": [
        {
          "keep_ratio": 0.3,
          "retrieval_ms": 0.005334,
          "scoring_ms": 118.4785,
          "pruning_ms": 0.07675000000000409,
          "ttft_ms": 3198.951625,
          "decode_tps": 16.023906726252818,
          "total_e2e_ms": 7561.171459000001,
          "generated_tokens": 68,
          "original_len": 12678,
          "compressed_len": 3515,
          "strategy": "static_ratio_30.0% (capped_at_10)"
        },
        {
          "keep_ratio": 0.3,
          "retrieval_ms": 0.0025,
          "scoring_ms": 119.842625,
          "pruning_ms": 0.061790999999999485,
          "ttft_ms": 134.500417,
          "decode_tps": 15.86852796695744,
          "total_e2e_ms": 6241.099999,
          "generated_tokens": 95,
          "original_len": 12678,
          "compressed_len": 3515,
          "strategy": "static_ratio_30.0% (capped_at_10)"
        },
        {
          "keep_ratio": 0.3,
          "retrieval_ms": 0.001541,
          "scoring_ms": 103.407833,
          "pruning_ms": 0.04083400000000381,
          "ttft_ms": 128.597709,
          "decode_tps": 15.520282901017541,
          "total_e2e_ms": 4677.843167,
          "generated_tokens": 69,
          "original_len": 12678,
          "compressed_len": 3515,
          "strategy": "static_ratio_30.0% (capped_at_10)"
        },
        {
          "keep_ratio": 0.3,
          "retrieval_ms": 0.001375,
          "scoring_ms": 109.385,
          "pruning_ms": 0.06287499999999113,
          "ttft_ms": 128.906166,
          "decode_tps": 15.787524100218262,
          "total_e2e_ms": 6635.812000000001,
          "generated_tokens": 101,
          "original_len": 12678,
          "compressed_len": 3515,
          "strategy": "static_ratio_30.0% (capped_at_10)"
        },
        {
          "keep_ratio": 0.3,
          "retrieval_ms": 0.001333,
          "scoring_ms": 101.828084,
          "pruning_ms": 0.042248999999998205,
          "ttft_ms": 130.667917,
          "decode_tps": 16.382586405008247,
          "total_e2e_ms": 2735.196916,
          "generated_tokens": 41,
          "original_len": 12678,
          "compressed_len": 3515,
          "strategy": "static_ratio_30.0% (capped_at_10)"
        }
      ],
      "selected_candidate": false,
      "strategies_used": [
        "static_ratio_30.0% (capped_at_10)"
      ],
      "retrieval_ms_mean": 0.002,
      "retrieval_ms_std": 0.002,
      "scoring_ms_mean": 110.588,
      "scoring_ms_std": 7.452,
      "pruning_ms_mean": 0.057,
      "pruning_ms_std": 0.014,
      "ttft_ms_mean": 744.325,
      "ttft_ms_std": 1227.315,
      "ttft_ms_p95": 2586.061,
      "decode_tps_mean": 15.917,
      "decode_tps_std": 0.284,
      "total_e2e_ms_mean": 5570.225,
      "total_e2e_ms_std": 1696.063,
      "total_e2e_ms_p95": 7376.1,
      "generated_tokens_mean": 74.8,
      "generated_tokens_std": 21.526,
      "original_len_mean": 12678.0,
      "original_len_std": 0.0,
      "compressed_len_mean": 3515.0,
      "compressed_len_std": 0.0
    },
    {
      "keep_ratio": 0.2,
      "runs": [
        {
          "keep_ratio": 0.2,
          "retrieval_ms": 0.001291,
          "scoring_ms": 99.561792,
          "pruning_ms": 0.06900000000000261,
          "ttft_ms": 2846.8625,
          "decode_tps": 15.894641411451522,
          "total_e2e_ms": 10433.2945,
          "generated_tokens": 119,
          "original_len": 12678,
          "compressed_len": 3248,
          "strategy": "static_ratio_20.0%"
        },
        {
          "keep_ratio": 0.2,
          "retrieval_ms": 0.001375,
          "scoring_ms": 108.937125,
          "pruning_ms": 0.04383300000000645,
          "ttft_ms": 130.975166,
          "decode_tps": 14.682827381404085,
          "total_e2e_ms": 9025.731291,
          "generated_tokens": 129,
          "original_len": 12678,
          "compressed_len": 3248,
          "strategy": "static_ratio_20.0%"
        },
        {
          "keep_ratio": 0.2,
          "retrieval_ms": 0.002292,
          "scoring_ms": 159.271208,
          "pruning_ms": 0.08166700000001015,
          "ttft_ms": 161.020625,
          "decode_tps": 13.727273654238079,
          "total_e2e_ms": 7240.905126,
          "generated_tokens": 95,
          "original_len": 12678,
          "compressed_len": 3248,
          "strategy": "static_ratio_20.0%"
        },
        {
          "keep_ratio": 0.2,
          "retrieval_ms": 0.002542,
          "scoring_ms": 126.984333,
          "pruning_ms": 0.07775099999999213,
          "ttft_ms": 141.329042,
          "decode_tps": 17.46272480522783,
          "total_e2e_ms": 5193.169209,
          "generated_tokens": 86,
          "original_len": 12678,
          "compressed_len": 3248,
          "strategy": "static_ratio_20.0%"
        },
        {
          "keep_ratio": 0.2,
          "retrieval_ms": 0.001209,
          "scoring_ms": 85.493875,
          "pruning_ms": 0.039082999999990875,
          "ttft_ms": 115.491208,
          "decode_tps": 16.825470117360858,
          "total_e2e_ms": 5193.456458,
          "generated_tokens": 84,
          "original_len": 12678,
          "compressed_len": 3248,
          "strategy": "static_ratio_20.0%"
        }
      ],
      "selected_candidate": false,
      "strategies_used": [
        "static_ratio_20.0%"
      ],
      "retrieval_ms_mean": 0.002,
      "retrieval_ms_std": 0.001,
      "scoring_ms_mean": 116.05,
      "scoring_ms_std": 25.471,
      "pruning_ms_mean": 0.062,
      "pruning_ms_std": 0.018,
      "ttft_ms_mean": 679.136,
      "ttft_ms_std": 1083.964,
      "ttft_ms_p95": 2309.694,
      "decode_tps_mean": 15.719,
      "decode_tps_std": 1.366,
      "total_e2e_ms_mean": 7417.311,
      "total_e2e_ms_std": 2078.78,
      "total_e2e_ms_p95": 10151.782,
      "generated_tokens_mean": 102.6,
      "generated_tokens_std": 18.139,
      "original_len_mean": 12678.0,
      "original_len_std": 0.0,
      "compressed_len_mean": 3248.0,
      "compressed_len_std": 0.0
    }
  ]
}